Metadata-Version: 2.1
Name: yellowpages-scraper
Version: 1.0.0
Summary: A python library to Scrape YellowPages.
Home-page: UNKNOWN
Author: DataKund
Author-email: datakund@gmail.com
License: Apache License 2.0
Keywords: yellow pages yellowpages python bot_studio automation product scraper city service
Platform: UNKNOWN
License-File: LICENSE
